[{"points": [{"flameEffect": null, "lingerTime": 0, "transitTime": 0, "y": 0.5, "x": 0.581875, "z": 0.5, "type": "passthrough"}, {"flameEffect": null, "lingerTime": 0, "transitTime": 1.4000000000000004, "y": 0.5, "x": 0.251875, "z": 0.5, "type": "passthrough"}], "name": "MyFavoriteTrigger"}, {"points": [{"flameEffect": "North South And Top", "lingerTime": 1, "transitTime": 0, "y": 0, "x": 0, "z": 0, "type": "linger"}, {"flameEffect": "NE", "lingerTime": 0.5, "transitTime": 2, "y": 0.031875, "x": 0.751875, "z": 0, "type": "passthrough"}, {"flameEffect": "Top", "lingerTime": 0.5, "transitTime": 2, "y": 1, "x": 0.171875, "z": 0, "type": "linger"}, {"flameEffect": null, "lingerTime": 0, "transitTime": 2, "y": 0.5, "x": 0.581875, "z": 0.5, "type": "passthrough"}], "name": "PassThrough"}, {"points": [{"flameEffect": null, "lingerTime": 0, "transitTime": 0, "y": 0.761875, "x": 0.5, "z": 0.5, "type": "passthrough"}, {"flameEffect": null, "lingerTime": 0, "transitTime": 0.29000000000000004, "y": 0.231875, "x": 0.5, "z": 0.5, "type": "passthrough"}, {"flameEffect": null, "lingerTime": 0, "transitTime": 2.96, "y": 0.671875, "x": 0.801875, "z": 0.191875, "type": "passthrough"}], "name": "MyThirdTrigger"}]